{
	"format_version": "1.12.0",
	"minecraft:geometry": [
		{
			"description": {
				"identifier": "geometry.telephone_block",
				"texture_width": 256,
				"texture_height": 256,
				"visible_bounds_width": 3,
				"visible_bounds_height": 2.5,
				"visible_bounds_offset": [0, 0.75, 0]
			},
			"bones": [
				{
					"name": "base",
					"pivot": [-8, 0, 8],
					"cubes": [
						{
							"origin": [3, 2, 6],
							"size": [1, 12, 1],
							"pivot": [0, 0, 0],
							"rotation": [-180, 0, 180],
							"uv": {
								"north": {"uv": [0, 0], "uv_size": [1, 1]},
								"east": {"uv": [0, 0], "uv_size": [1, 1]},
								"south": {"uv": [0, 0], "uv_size": [1, 1]},
								"west": {"uv": [0, 0], "uv_size": [1, 1]},
								"up": {"uv": [1, 1], "uv_size": [-1, -1]},
								"down": {"uv": [1, 1], "uv_size": [-1, -1]}
							}
						},
						{
							"origin": [-4, 2, 7],
							"size": [8, 12, 1],
							"pivot": [0, 0, 0],
							"rotation": [-180, 0, 180],
							"uv": {
								"north": {"uv": [0, 0], "uv_size": [1, 1]},
								"east": {"uv": [0, 0], "uv_size": [1, 1]},
								"south": {"uv": [0, 0], "uv_size": [1, 1]},
								"west": {"uv": [0, 0], "uv_size": [1, 1]},
								"up": {"uv": [1, 1], "uv_size": [-1, -1]},
								"down": {"uv": [1, 1], "uv_size": [-1, -1]}
							}
						},
						{
							"origin": [-4, 2, 6],
							"size": [1, 12, 1],
							"pivot": [0, 0, 0],
							"rotation": [-180, 0, 180],
							"uv": {
								"north": {"uv": [0, 0], "uv_size": [1, 1]},
								"east": {"uv": [0, 0], "uv_size": [1, 1]},
								"south": {"uv": [0, 0], "uv_size": [1, 1]},
								"west": {"uv": [0, 0], "uv_size": [1, 1]},
								"up": {"uv": [1, 1], "uv_size": [-1, -1]},
								"down": {"uv": [1, 1], "uv_size": [-1, -1]}
							}
						}
					]
				},
				{
					"name": "buttons",
					"pivot": [-8, 8, 8]
				},
				{
					"name": "button_1",
					"parent": "buttons",
					"pivot": [-8, 8, 8],
					"cubes": [
						{
							"origin": [-2.75, 10.25, 6],
							"size": [1.5, 1.5, 1],
							"pivot": [0, 0, 0],
							"rotation": [-180, 0, 180],
							"uv": {
								"north": {"uv": [7, 12], "uv_size": [1, 1]},
								"east": {"uv": [7, 12], "uv_size": [1, 1]},
								"south": {"uv": [7, 12], "uv_size": [1, 1]},
								"west": {"uv": [7, 12], "uv_size": [1, 1]},
								"up": {"uv": [8, 13], "uv_size": [-1, -1]},
								"down": {"uv": [8, 13], "uv_size": [-1, -1]}
							}
						},
						{
							"origin": [-2.65, 10.15, 5.99],
							"size": [1.5, 1.5, 1],
							"pivot": [0, 0, 0],
							"rotation": [-180, 0, 180],
							"uv": {
								"north": {"uv": [23, 24], "uv_size": [8, 8]}
							}
						}
					]
				},
				{
					"name": "button_2",
					"parent": "buttons",
					"pivot": [-8, 8, 8],
					"cubes": [
						{
							"origin": [-0.75, 10.25, 6],
							"size": [1.5, 1.5, 1],
							"pivot": [0, 0, 0],
							"rotation": [-180, 0, 180],
							"uv": {
								"north": {"uv": [7, 12], "uv_size": [1, 1]},
								"east": {"uv": [7, 12], "uv_size": [1, 1]},
								"south": {"uv": [7, 12], "uv_size": [1, 1]},
								"west": {"uv": [7, 12], "uv_size": [1, 1]},
								"up": {"uv": [8, 13], "uv_size": [-1, -1]},
								"down": {"uv": [8, 13], "uv_size": [-1, -1]}
							}
						},
						{
							"origin": [-0.65, 10.15, 5.99],
							"size": [1.5, 1.5, 1],
							"pivot": [0, 0, 0],
							"rotation": [-180, 0, 180],
							"uv": {
								"north": {"uv": [31, 24], "uv_size": [8, 8]}
							}
						}
					]
				},
				{
					"name": "button_3",
					"parent": "buttons",
					"pivot": [-8, 8, 8],
					"cubes": [
						{
							"origin": [1.25, 10.25, 6],
							"size": [1.5, 1.5, 1],
							"pivot": [0, 0, 0],
							"rotation": [-180, 0, 180],
							"uv": {
								"north": {"uv": [7, 12], "uv_size": [1, 1]},
								"east": {"uv": [7, 12], "uv_size": [1, 1]},
								"south": {"uv": [7, 12], "uv_size": [1, 1]},
								"west": {"uv": [7, 12], "uv_size": [1, 1]},
								"up": {"uv": [8, 13], "uv_size": [-1, -1]},
								"down": {"uv": [8, 13], "uv_size": [-1, -1]}
							}
						},
						{
							"origin": [1.35, 10.15, 5.99],
							"size": [1.5, 1.5, 1],
							"pivot": [0, 0, 0],
							"rotation": [-180, 0, 180],
							"uv": {
								"north": {"uv": [39, 24], "uv_size": [8, 8]}
							}
						}
					]
				},
				{
					"name": "button_4",
					"parent": "buttons",
					"pivot": [-8, 8, 8],
					"cubes": [
						{
							"origin": [-2.75, 8.25, 6],
							"size": [1.5, 1.5, 1],
							"pivot": [0, 0, 0],
							"rotation": [-180, 0, 180],
							"uv": {
								"north": {"uv": [7, 12], "uv_size": [1, 1]},
								"east": {"uv": [7, 12], "uv_size": [1, 1]},
								"south": {"uv": [7, 12], "uv_size": [1, 1]},
								"west": {"uv": [7, 12], "uv_size": [1, 1]},
								"up": {"uv": [8, 13], "uv_size": [-1, -1]},
								"down": {"uv": [8, 13], "uv_size": [-1, -1]}
							}
						},
						{
							"origin": [-2.65, 8.15, 5.99],
							"size": [1.5, 1.5, 1],
							"pivot": [0, 0, 0],
							"rotation": [-180, 0, 180],
							"uv": {
								"north": {"uv": [47, 24], "uv_size": [8, 8]}
							}
						}
					]
				},
				{
					"name": "button_5",
					"parent": "buttons",
					"pivot": [-8, 8, 8],
					"cubes": [
						{
							"origin": [-0.75, 8.25, 6],
							"size": [1.5, 1.5, 1],
							"pivot": [0, 0, 0],
							"rotation": [-180, 0, 180],
							"uv": {
								"north": {"uv": [7, 12], "uv_size": [1, 1]},
								"east": {"uv": [7, 12], "uv_size": [1, 1]},
								"south": {"uv": [7, 12], "uv_size": [1, 1]},
								"west": {"uv": [7, 12], "uv_size": [1, 1]},
								"up": {"uv": [8, 13], "uv_size": [-1, -1]},
								"down": {"uv": [8, 13], "uv_size": [-1, -1]}
							}
						},
						{
							"origin": [-0.65, 8.15, 5.99],
							"size": [1.5, 1.5, 1],
							"pivot": [0, 0, 0],
							"rotation": [-180, 0, 180],
							"uv": {
								"north": {"uv": [55, 24], "uv_size": [8, 8]}
							}
						}
					]
				},
				{
					"name": "button_6",
					"parent": "buttons",
					"pivot": [-8, 8, 8],
					"cubes": [
						{
							"origin": [1.25, 8.25, 6],
							"size": [1.5, 1.5, 1],
							"pivot": [0, 0, 0],
							"rotation": [-180, 0, 180],
							"uv": {
								"north": {"uv": [7, 12], "uv_size": [1, 1]},
								"east": {"uv": [7, 12], "uv_size": [1, 1]},
								"south": {"uv": [7, 12], "uv_size": [1, 1]},
								"west": {"uv": [7, 12], "uv_size": [1, 1]},
								"up": {"uv": [8, 13], "uv_size": [-1, -1]},
								"down": {"uv": [8, 13], "uv_size": [-1, -1]}
							}
						},
						{
							"origin": [1.35, 8.15, 5.99],
							"size": [1.5, 1.5, 1],
							"pivot": [0, 0, 0],
							"rotation": [-180, 0, 180],
							"uv": {
								"north": {"uv": [63, 24], "uv_size": [8, 8]}
							}
						}
					]
				},
				{
					"name": "button_7",
					"parent": "buttons",
					"pivot": [-8, 8, 8],
					"cubes": [
						{
							"origin": [-2.75, 6.25, 6],
							"size": [1.5, 1.5, 1],
							"pivot": [0, 0, 0],
							"rotation": [-180, 0, 180],
							"uv": {
								"north": {"uv": [7, 12], "uv_size": [1, 1]},
								"east": {"uv": [7, 12], "uv_size": [1, 1]},
								"south": {"uv": [7, 12], "uv_size": [1, 1]},
								"west": {"uv": [7, 12], "uv_size": [1, 1]},
								"up": {"uv": [8, 13], "uv_size": [-1, -1]},
								"down": {"uv": [8, 13], "uv_size": [-1, -1]}
							}
						},
						{
							"origin": [-2.65, 6.15, 5.99],
							"size": [1.5, 1.5, 1],
							"pivot": [0, 0, 0],
							"rotation": [-180, 0, 180],
							"uv": {
								"north": {"uv": [71, 24], "uv_size": [8, 8]}
							}
						}
					]
				},
				{
					"name": "button_8",
					"parent": "buttons",
					"pivot": [-8, 8, 8],
					"cubes": [
						{
							"origin": [-0.75, 6.25, 6],
							"size": [1.5, 1.5, 1],
							"pivot": [0, 0, 0],
							"rotation": [-180, 0, 180],
							"uv": {
								"north": {"uv": [7, 12], "uv_size": [1, 1]},
								"east": {"uv": [7, 12], "uv_size": [1, 1]},
								"south": {"uv": [7, 12], "uv_size": [1, 1]},
								"west": {"uv": [7, 12], "uv_size": [1, 1]},
								"up": {"uv": [8, 13], "uv_size": [-1, -1]},
								"down": {"uv": [8, 13], "uv_size": [-1, -1]}
							}
						},
						{
							"origin": [-0.65, 6.15, 5.99],
							"size": [1.5, 1.5, 1],
							"pivot": [0, 0, 0],
							"rotation": [-180, 0, 180],
							"uv": {
								"north": {"uv": [79, 24], "uv_size": [8, 8]}
							}
						}
					]
				},
				{
					"name": "button_9",
					"parent": "buttons",
					"pivot": [-8, 8, 8],
					"cubes": [
						{
							"origin": [1.25, 6.25, 6],
							"size": [1.5, 1.5, 1],
							"pivot": [0, 0, 0],
							"rotation": [-180, 0, 180],
							"uv": {
								"north": {"uv": [7, 12], "uv_size": [1, 1]},
								"east": {"uv": [7, 12], "uv_size": [1, 1]},
								"south": {"uv": [7, 12], "uv_size": [1, 1]},
								"west": {"uv": [7, 12], "uv_size": [1, 1]},
								"up": {"uv": [8, 13], "uv_size": [-1, -1]},
								"down": {"uv": [8, 13], "uv_size": [-1, -1]}
							}
						},
						{
							"origin": [1.35, 6.15, 5.99],
							"size": [1.5, 1.5, 1],
							"pivot": [0, 0, 0],
							"rotation": [-180, 0, 180],
							"uv": {
								"north": {"uv": [87, 24], "uv_size": [8, 8]}
							}
						}
					]
				},
				{
					"name": "button_star",
					"parent": "buttons",
					"pivot": [-8, 8, 8],
					"cubes": [
						{
							"origin": [-2.75, 4.25, 6],
							"size": [1.5, 1.5, 1],
							"pivot": [0, 0, 0],
							"rotation": [-180, 0, 180],
							"uv": {
								"north": {"uv": [7, 12], "uv_size": [1, 1]},
								"east": {"uv": [7, 12], "uv_size": [1, 1]},
								"south": {"uv": [7, 12], "uv_size": [1, 1]},
								"west": {"uv": [7, 12], "uv_size": [1, 1]},
								"up": {"uv": [8, 13], "uv_size": [-1, -1]},
								"down": {"uv": [8, 13], "uv_size": [-1, -1]}
							}
						},
						{
							"origin": [-2.65, 4.15, 5.99],
							"size": [1.5, 1.5, 1],
							"pivot": [0, 0, 0],
							"rotation": [-180, 0, 180],
							"uv": {
								"north": {"uv": [93, 15], "uv_size": [10, 10]}
							}
						}
					]
				},
				{
					"name": "button_0",
					"parent": "buttons",
					"pivot": [-8, 8, 8],
					"cubes": [
						{
							"origin": [-0.75, 4.25, 6],
							"size": [1.5, 1.5, 1],
							"pivot": [0, 0, 0],
							"rotation": [-180, 0, 180],
							"uv": {
								"north": {"uv": [7, 12], "uv_size": [1, 1]},
								"east": {"uv": [7, 12], "uv_size": [1, 1]},
								"south": {"uv": [7, 12], "uv_size": [1, 1]},
								"west": {"uv": [7, 12], "uv_size": [1, 1]},
								"up": {"uv": [8, 13], "uv_size": [-1, -1]},
								"down": {"uv": [8, 13], "uv_size": [-1, -1]}
							}
						},
						{
							"origin": [-0.45, 4.15, 5.99],
							"size": [1.5, 1.5, 1],
							"pivot": [0, 0, 0],
							"rotation": [-180, 0, 180],
							"uv": {
								"north": {"uv": [16, 24], "uv_size": [8, 8]}
							}
						}
					]
				},
				{
					"name": "button_pound",
					"parent": "buttons",
					"pivot": [-8, 8, 8],
					"cubes": [
						{
							"origin": [1.25, 4.25, 6],
							"size": [1.5, 1.5, 1],
							"pivot": [0, 0, 0],
							"rotation": [-180, 0, 180],
							"uv": {
								"north": {"uv": [7, 12], "uv_size": [1, 1]},
								"east": {"uv": [7, 12], "uv_size": [1, 1]},
								"south": {"uv": [7, 12], "uv_size": [1, 1]},
								"west": {"uv": [7, 12], "uv_size": [1, 1]},
								"up": {"uv": [8, 13], "uv_size": [-1, -1]},
								"down": {"uv": [8, 13], "uv_size": [-1, -1]}
							}
						},
						{
							"origin": [1.35, 4.15, 5.99],
							"size": [1.5, 1.5, 1],
							"pivot": [0, 0, 0],
							"rotation": [-180, 0, 180],
							"uv": {
								"north": {"uv": [39, 16], "uv_size": [8, 8]}
							}
						}
					]
				},
				{
					"name": "VoxelShapes",
					"pivot": [-8, 0, 8],
					"cubes": [
						{
							"origin": [-4, 2, 7],
							"size": [8, 12, 1],
							"pivot": [0, 0, 0],
							"rotation": [-180, 0, 180],
							"uv": {}
						},
						{
							"origin": [-4, 2, 6],
							"size": [1, 12, 1],
							"pivot": [0, 0, 0],
							"rotation": [-180, 0, 180],
							"uv": {}
						},
						{
							"origin": [3, 2, 6],
							"size": [1, 12, 1],
							"pivot": [0, 0, 0],
							"rotation": [-180, 0, 180],
							"uv": {}
						},
						{
							"origin": [-2.75, 10.25, 6],
							"size": [1.5, 1.5, 1],
							"pivot": [0, 0, 0],
							"rotation": [-180, 0, 180],
							"uv": {}
						},
						{
							"origin": [-0.75, 10.25, 6],
							"size": [1.5, 1.5, 1],
							"pivot": [0, 0, 0],
							"rotation": [-180, 0, 180],
							"uv": {}
						},
						{
							"origin": [1.25, 10.25, 6],
							"size": [1.5, 1.5, 1],
							"pivot": [0, 0, 0],
							"rotation": [-180, 0, 180],
							"uv": {}
						},
						{
							"origin": [1.25, 8.25, 6],
							"size": [1.5, 1.5, 1],
							"pivot": [0, 0, 0],
							"rotation": [-180, 0, 180],
							"uv": {}
						},
						{
							"origin": [-0.75, 8.25, 6],
							"size": [1.5, 1.5, 1],
							"pivot": [0, 0, 0],
							"rotation": [-180, 0, 180],
							"uv": {}
						},
						{
							"origin": [-2.75, 8.25, 6],
							"size": [1.5, 1.5, 1],
							"pivot": [0, 0, 0],
							"rotation": [-180, 0, 180],
							"uv": {}
						},
						{
							"origin": [-2.75, 6.25, 6],
							"size": [1.5, 1.5, 1],
							"pivot": [0, 0, 0],
							"rotation": [-180, 0, 180],
							"uv": {}
						},
						{
							"origin": [-0.75, 6.25, 6],
							"size": [1.5, 1.5, 1],
							"pivot": [0, 0, 0],
							"rotation": [-180, 0, 180],
							"uv": {}
						},
						{
							"origin": [1.25, 6.25, 6],
							"size": [1.5, 1.5, 1],
							"pivot": [0, 0, 0],
							"rotation": [-180, 0, 180],
							"uv": {}
						},
						{
							"origin": [1.25, 4.25, 6],
							"size": [1.5, 1.5, 1],
							"pivot": [0, 0, 0],
							"rotation": [-180, 0, 180],
							"uv": {}
						},
						{
							"origin": [-0.75, 4.25, 6],
							"size": [1.5, 1.5, 1],
							"pivot": [0, 0, 0],
							"rotation": [-180, 0, 180],
							"uv": {}
						},
						{
							"origin": [-2.75, 4.25, 6],
							"size": [1.5, 1.5, 1],
							"pivot": [0, 0, 0],
							"rotation": [-180, 0, 180],
							"uv": {}
						}
					]
				},
				{
					"name": "VoxelShapesCombined",
					"pivot": [-8, 0, 8],
					"cubes": [
						{
							"origin": [-4, 2, 5],
							"size": [8, 12, 3],
							"pivot": [0, 0, 0],
							"rotation": [-180, 0, 180],
							"uv": {}
						}
					]
				},
				{
					"name": "handsetBone",
					"pivot": [0, 0, 0],
					"cubes": [
						{
							"origin": [-3, 2, 5],
							"size": [6, 12, 2],
							"pivot": [0, 0, 0],
							"rotation": [-180, 0, 180],
							"uv": {
								"north": {"uv": [5, 2], "uv_size": [6, 12]},
								"east": {"uv": [0, 0], "uv_size": [1, 1]},
								"south": {"uv": [0, 0], "uv_size": [1, 1]},
								"west": {"uv": [11, 2], "uv_size": [2, 12]},
								"up": {"uv": [1, 1], "uv_size": [-1, -1]},
								"down": {"uv": [1, 1], "uv_size": [-1, -1]}
							}
						}
					]
				}
			]
		}
	]
}